sqlalchemy_timescaledb/__init__.py
sqlalchemy_timescaledb/dialect.py
sqlalchemy_timescaledb/functions.py
sqlalchemy_timescaledb-0.4.1.dist-info/LICENSE
sqlalchemy_timescaledb-0.4.1.dist-info/METADATA
sqlalchemy_timescaledb-0.4.1.dist-info/WHEEL
sqlalchemy_timescaledb-0.4.1.dist-info/entry_points.txt
sqlalchemy_timescaledb-0.4.1.dist-info/top_level.txt
sqlalchemy_timescaledb-0.4.1.dist-info/RECORD
