Metadata-Version: 2.1
Name: sqlalchemy-timescaledb
Version: 0.4.1
Summary: A SQLAlchemy dialect for TimescaleDB
Author-email: Andrei Kliatsko <andrey.daraschenka@gmail.com>
Project-URL: Homepage, https://github.com/dorosch/sqlalchemy-timescaledb
Provides-Extra: test
License-File: LICENSE
